MANIFEST.in
README.rst
install_conda_packages.bat
install_conda_packages.sh
setup.py
geospatial_learn/__init__.py
geospatial_learn/data.py
geospatial_learn/gdal_merge.py
geospatial_learn/geodata.py
geospatial_learn/handyplots.py
geospatial_learn/learning.py
geospatial_learn/shape.py
geospatial_learn/utilities.py
geospatial_learn.egg-info/PKG-INFO
geospatial_learn.egg-info/SOURCES.txt
geospatial_learn.egg-info/dependency_links.txt
geospatial_learn.egg-info/requires.txt
geospatial_learn.egg-info/top_level.txt