Metadata-Version: 1.1
Name: geospatial-learn
Version: 0.129
Summary: geospatial-learn is a Python module for using scikit-learn andxgb models with geo-spatial data, chiefly raster and vectorformats.
Home-page: https://github.com/Ciaran1981/geospatial-learn
Author: Ciaran Robb
Author-email: UNKNOWN
License: GPLv3+
Platform: UNKNOWN
Classifier: License :: OSI Approved :: GNU General Public License v3 or later (GPLv3+)
Classifier: Programming Language :: Python :: 3.4
Classifier: Programming Language :: Python :: 3.5
Classifier: Programming Language :: Python :: 3.6
Classifier: Topic :: Scientific/Engineering :: GIS
Classifier: Topic :: Utilities
